ossin/__init__.py
ossin/__main__.py
ossin/_version.py
ossin/cli.py
ossin/core.py
ossin/py.typed
ossin-0.1.1.dist-info/METADATA
ossin-0.1.1.dist-info/WHEEL
ossin-0.1.1.dist-info/entry_points.txt
ossin-0.1.1.dist-info/licenses/LICENSE
ossin-0.1.1.dist-info/RECORD
