Metadata-Version: 2.4
Name: ossin
Version: 0.1.1
Summary: What is OS's sin? 🤔 A beautiful system information utility that displays basic information about your operating system, Python environment, and platform details using Rich for stunning terminal output.
Project-URL: changelog, https://github.com/python-ankara-toplulugu/ossin/blob/main/CHANGELOG.md
Project-URL: documentation, https://github.com/python-ankara-toplulugu/ossin#readme
Project-URL: homepage, https://github.com/python-ankara-toplulugu/ossin
Project-URL: issues, https://github.com/python-ankara-toplulugu/ossin/issues
Project-URL: releasenotes, https://github.com/python-ankara-toplulugu/ossin/releases
Project-URL: source, https://github.com/python-ankara-toplulugu/ossin.git
Author-email: Hasan Sezer Taşan <hasansezertasan@gmail.com>
Maintainer-email: Hasan Sezer Taşan <hasansezertasan@gmail.com>
License-Expression: MIT
License-File: LICENSE
Keywords: cli,command-line,information,monitoring,ossin,system,utility
Classifier: Development Status :: 4 - Beta
Classifier: Environment :: Console
Classifier: Intended Audience :: Developers
Classifier: Intended Audience :: Information Technology
Classifier: Intended Audience :: System Administrators
Classifier: License :: OSI Approved :: MIT License
Classifier: Operating System :: OS Independent
Classifier: Programming Language :: Python
Classifier: Programming Language :: Python :: 3
Classifier: Programming Language :: Python :: 3 :: Only
Classifier: Programming Language :: Python :: 3.8
Classifier: Programming Language :: Python :: 3.9
Classifier: Programming Language :: Python :: 3.10
Classifier: Programming Language :: Python :: 3.11
Classifier: Programming Language :: Python :: 3.12
Classifier: Programming Language :: Python :: 3.13
Classifier: Programming Language :: Python :: 3.14
Classifier: Programming Language :: Python :: Implementation :: CPython
Classifier: Programming Language :: Python :: Implementation :: PyPy
Classifier: Topic :: Software Development
Classifier: Topic :: Software Development :: Libraries
Classifier: Topic :: Software Development :: Libraries :: Python Modules
Classifier: Topic :: Terminals
Classifier: Typing :: Typed
Requires-Python: >=3.8
Requires-Dist: typer>=0.16.0
Provides-Extra: cli
Requires-Dist: typer; extra == 'cli'
